{
    "asreviewVersion": "1.2",
    "apiVersion": "1.1.2",
    "data": {
        "items": [
            {
                "id": "recall",
                "title": "Recall",
                "value": [
                    [
                        0.1,
                        0.9787234042553191
                    ],
                    [
                        0.25,
                        1.0
                    ],
                    [
                        0.5,
                        1.0
                    ],
                    [
                        0.75,
                        1.0
                    ],
                    [
                        0.9,
                        1.0
                    ]
                ]
            },
            {
                "id": "wss",
                "title": "Work Saved over Sampling",
                "value": [
                    [
                        0.95,
                        0.869182602809274
                    ]
                ]
            },
            {
                "id": "erf",
                "title": "Extra Relevant record Found",
                "value": [
                    [
                        0.1,
                        0.8723404255319149
                    ]
                ]
            },
            {
                "id": "atd",
                "title": "Average time to discovery",
                "value": 160.91489361702128
            },
            {
                "id": "td",
                "title": "Time to discovery",
                "value": [
                    [
                        3932,
                        1,
                        1
                    ],
                    [
                        5034,
                        2,
                        2
                    ],
                    [
                        2475,
                        5,
                        3
                    ],
                    [
                        588,
                        6,
                        4
                    ],
                    [
                        1959,
                        8,
                        5
                    ],
                    [
                        4990,
                        9,
                        6
                    ],
                    [
                        4056,
                        11,
                        7
                    ],
                    [
                        88,
                        13,
                        8
                    ],
                    [
                        734,
                        15,
                        9
                    ],
                    [
                        542,
                        16,
                        10
                    ],
                    [
                        3186,
                        19,
                        11
                    ],
                    [
                        490,
                        24,
                        12
                    ],
                    [
                        1888,
                        25,
                        13
                    ],
                    [
                        733,
                        29,
                        14
                    ],
                    [
                        4924,
                        59,
                        15
                    ],
                    [
                        1405,
                        62,
                        16
                    ],
                    [
                        2377,
                        68,
                        17
                    ],
                    [
                        400,
                        75,
                        18
                    ],
                    [
                        5386,
                        78,
                        19
                    ],
                    [
                        2768,
                        80,
                        20
                    ],
                    [
                        3142,
                        91,
                        21
                    ],
                    [
                        5746,
                        92,
                        22
                    ],
                    [
                        3529,
                        94,
                        23
                    ],
                    [
                        2010,
                        100,
                        24
                    ],
                    [
                        5492,
                        121,
                        25
                    ],
                    [
                        2255,
                        128,
                        26
                    ],
                    [
                        624,
                        132,
                        27
                    ],
                    [
                        3230,
                        157,
                        28
                    ],
                    [
                        5332,
                        185,
                        29
                    ],
                    [
                        3376,
                        192,
                        30
                    ],
                    [
                        4597,
                        196,
                        31
                    ],
                    [
                        3621,
                        199,
                        32
                    ],
                    [
                        5147,
                        205,
                        33
                    ],
                    [
                        2640,
                        217,
                        34
                    ],
                    [
                        1891,
                        218,
                        35
                    ],
                    [
                        4241,
                        219,
                        36
                    ],
                    [
                        4842,
                        220,
                        37
                    ],
                    [
                        4592,
                        222,
                        38
                    ],
                    [
                        753,
                        253,
                        39
                    ],
                    [
                        758,
                        254,
                        40
                    ],
                    [
                        4421,
                        263,
                        41
                    ],
                    [
                        1395,
                        266,
                        42
                    ],
                    [
                        466,
                        271,
                        43
                    ],
                    [
                        2398,
                        334,
                        44
                    ],
                    [
                        4826,
                        466,
                        45
                    ],
                    [
                        5655,
                        505,
                        46
                    ],
                    [
                        2312,
                        1358,
                        47
                    ]
                ]
            }
        ]
    }
}